[{"id": 1, "type": "EVENT", "subject": null, "predicate": null, "object": null, "description": " The round payoff this round was 1. You, Kate chose to play option 1.John chose to play option 1. You received a payoff of 0.", "importance_score": 10, "created": "2024-01-02 01:00:00", "expiration": "2024-04-30 01:00:00", "always_include": "true"}, {"id": 2, "type": "THOUGHT", "subject": null, "predicate": null, "object": null, "description": "Mutual cooperation (choosing 1) is the safest strategy to avoid catastrophic losses", "importance_score": 8, "created": "2024-01-31 01:00:00", "expiration": "2024-05-10 01:00:00", "always_include": "false"}, {"id": 3, "type": "THOUGHT", "subject": null, "predicate": null, "object": null, "description": "Defecting (choosing 2) risks triggering mutual punishment (input \u00d7 1000 loss) if John adapts, outweighing short-term gains", "importance_score": 8, "created": "2024-01-31 01:00:00", "expiration": "2024-05-10 01:00:00", "always_include": "false"}, {"id": 4, "type": "THOUGHT", "subject": null, "predicate": null, "object": null, "description": "The game incentivizes stable cooperation due to asymmetric payoffs favoring risk aversion", "importance_score": 8, "created": "2024-01-31 01:00:00", "expiration": "2024-05-10 01:00:00", "always_include": "false"}]